{
	"configurations" : 
	[
		{
			"abstractTargets" : 
			[
				{
					"directoryIndex" : 0,
					"id" : "Boost::boost::@6890427a1f51a3e7e1df",
					"jsonFile" : "target-Boost__boost-86a3d682ebcc5e57808e.json",
					"name" : "Boost::boost",
					"projectIndex" : 0
				},
				{
					"directoryIndex" : 0,
					"id" : "Boost::diagnostic_definitions::@6890427a1f51a3e7e1df",
					"jsonFile" : "target-Boost__diagnostic_definitions-c2b72e4bdcc167575698.json",
					"name" : "Boost::diagnostic_definitions",
					"projectIndex" : 0
				},
				{
					"directoryIndex" : 0,
					"id" : "Boost::disable_autolinking::@6890427a1f51a3e7e1df",
					"jsonFile" : "target-Boost__disable_autolinking-1d977f76b53ac7579a88.json",
					"name" : "Boost::disable_autolinking",
					"projectIndex" : 0
				},
				{
					"directoryIndex" : 0,
					"id" : "Boost::dynamic_linking::@6890427a1f51a3e7e1df",
					"jsonFile" : "target-Boost__dynamic_linking-5644751fc5dbb1ca461b.json",
					"name" : "Boost::dynamic_linking",
					"projectIndex" : 0
				},
				{
					"directoryIndex" : 0,
					"id" : "Boost::headers::@6890427a1f51a3e7e1df",
					"jsonFile" : "target-Boost__headers-238bc01b67640c9f47c9.json",
					"name" : "Boost::headers",
					"projectIndex" : 0
				},
				{
					"directoryIndex" : 0,
					"id" : "GTest::GTest::@6890427a1f51a3e7e1df",
					"jsonFile" : "target-GTest__GTest-4e679481b226ea0ade1d.json",
					"name" : "GTest::GTest",
					"projectIndex" : 0
				},
				{
					"directoryIndex" : 0,
					"id" : "GTest::Main::@6890427a1f51a3e7e1df",
					"jsonFile" : "target-GTest__Main-7d0d01328e32eb7440e9.json",
					"name" : "GTest::Main",
					"projectIndex" : 0
				},
				{
					"directoryIndex" : 0,
					"id" : "GTest::gmock::@6890427a1f51a3e7e1df",
					"jsonFile" : "target-GTest__gmock-daed475e3b828a2de53f.json",
					"name" : "GTest::gmock",
					"projectIndex" : 0
				},
				{
					"directoryIndex" : 0,
					"id" : "GTest::gmock_main::@6890427a1f51a3e7e1df",
					"jsonFile" : "target-GTest__gmock_main-cd0dbfe73ad4cfd4c62c.json",
					"name" : "GTest::gmock_main",
					"projectIndex" : 0
				},
				{
					"directoryIndex" : 0,
					"id" : "GTest::gtest::@6890427a1f51a3e7e1df",
					"jsonFile" : "target-GTest__gtest-54cd2345d6fd5f26ef0c.json",
					"name" : "GTest::gtest",
					"projectIndex" : 0
				},
				{
					"directoryIndex" : 0,
					"id" : "GTest::gtest_main::@6890427a1f51a3e7e1df",
					"jsonFile" : "target-GTest__gtest_main-c60786b15a18a91acf30.json",
					"name" : "GTest::gtest_main",
					"projectIndex" : 0
				},
				{
					"directoryIndex" : 0,
					"id" : "Threads::Threads::@6890427a1f51a3e7e1df",
					"jsonFile" : "target-Threads__Threads-4eee455fbbb347b95cd6.json",
					"name" : "Threads::Threads",
					"projectIndex" : 0
				}
			],
			"directories" : 
			[
				{
					"abstractTargetIndexes" : 
					[
						0,
						1,
						2,
						3,
						4,
						5,
						6,
						7,
						8,
						9,
						10,
						11
					],
					"build" : ".",
					"jsonFile" : "directory-.-9ad1a58d4644cf6543fa.json",
					"minimumCMakeVersion" : 
					{
						"string" : "3.20"
					},
					"projectIndex" : 0,
					"source" : ".",
					"targetIndexes" : 
					[
						0,
						1,
						2,
						3
					]
				}
			],
			"name" : "",
			"projects" : 
			[
				{
					"abstractTargetIndexes" : 
					[
						0,
						1,
						2,
						3,
						4,
						5,
						6,
						7,
						8,
						9,
						10,
						11
					],
					"directoryIndexes" : 
					[
						0
					],
					"name" : "LiteExchange",
					"targetIndexes" : 
					[
						0,
						1,
						2,
						3
					]
				}
			],
			"targets" : 
			[
				{
					"directoryIndex" : 0,
					"id" : "client::@6890427a1f51a3e7e1df",
					"jsonFile" : "target-client-e798052894d826e0d890.json",
					"name" : "client",
					"projectIndex" : 0
				},
				{
					"directoryIndex" : 0,
					"id" : "exchange::@6890427a1f51a3e7e1df",
					"jsonFile" : "target-exchange-c029c76a8fa8f75c4f17.json",
					"name" : "exchange",
					"projectIndex" : 0
				},
				{
					"directoryIndex" : 0,
					"id" : "exchange_lib::@6890427a1f51a3e7e1df",
					"jsonFile" : "target-exchange_lib-62e6a1dc2ca227c12c6b.json",
					"name" : "exchange_lib",
					"projectIndex" : 0
				},
				{
					"directoryIndex" : 0,
					"id" : "fix_tests::@6890427a1f51a3e7e1df",
					"jsonFile" : "target-fix_tests-a415ed8410417d1ec32c.json",
					"name" : "fix_tests",
					"projectIndex" : 0
				}
			]
		}
	],
	"kind" : "codemodel",
	"paths" : 
	{
		"build" : "/Users/chriskontsis/Desktop/Lite-Exchange/build",
		"source" : "/Users/chriskontsis/Desktop/Lite-Exchange"
	},
	"version" : 
	{
		"major" : 2,
		"minor" : 9
	}
}
